typings_google_calendar_api/__init__.py
typings_google_calendar_api/acl.py
typings_google_calendar_api/calendars.py
typings_google_calendar_api/colors.py
typings_google_calendar_api/events.py
typings_google_calendar_api-1.0.0.dist-info/LICENSE
typings_google_calendar_api-1.0.0.dist-info/METADATA
typings_google_calendar_api-1.0.0.dist-info/WHEEL
typings_google_calendar_api-1.0.0.dist-info/top_level.txt
typings_google_calendar_api-1.0.0.dist-info/RECORD
