Metadata-Version: 2.1
Name: typings-google-calendar-api
Version: 1.0.0
Summary: Python typehint support for Google Calendar API resources
Home-page: https://github.com/lazarofl/typings-google-calendar-api
Author: Lazaro Suleiman
Author-email: lazaro.fl@gmail.com
License: UNKNOWN
Platform: UNKNOWN
Classifier: Programming Language :: Python :: 3
Classifier: License :: OSI Approved :: MIT License
Classifier: Operating System :: OS Independent
Requires-Dist: typing-extensions
